SAPB1SL/__init__.py
SAPB1SL/client.py
SAPB1SL/exceptions.py
sapb1sl-2.0.0.dist-info/licenses/LICENSE
sapb1sl-2.0.0.dist-info/METADATA
sapb1sl-2.0.0.dist-info/WHEEL
sapb1sl-2.0.0.dist-info/top_level.txt
sapb1sl-2.0.0.dist-info/RECORD
