Metadata-Version: 2.4
Name: SAPB1SL
Version: 2.0.0
Summary: Cliente Python para el Service Layer de SAP Business One usando requests.
Home-page: https://github.com/Bryanluispg/SAPB1SL
Author: Bryan Pineda Gonzalez
Author-email: dev@bryanlpinedag.com
License: MIT
Classifier: Programming Language :: Python :: 3
Classifier: Operating System :: OS Independent
Requires-Python: >=3.7
License-File: LICENSE
Requires-Dist: requests
Requires-Dist: urllib3
Dynamic: author
Dynamic: author-email
Dynamic: classifier
Dynamic: description
Dynamic: description-content-type
Dynamic: home-page
Dynamic: license
Dynamic: license-file
Dynamic: requires-dist
Dynamic: requires-python
Dynamic: summary
